Metadata-Version: 1.0
Name: BEANS-GS
Version: 1.2
Summary: BEANS
Home-page: UNKNOWN
Author: Gurnek
Author-email: UNKNOWN
License: UNKNOWN
Platform: UNKNOWN
